jupyterlab_notechat/__init__.py
jupyterlab_notechat/_version.py
jupyterlab_notechat/handlers.py
jupyterlab_notechat/tests/__init__.py
jupyterlab_notechat/tests/test_handlers.py
jupyterlab_notechat-1.2.4.data/data/etc/jupyter/jupyter_server_config.d/jupyterlab_notechat.json
jupyterlab_notechat-1.2.4.data/data/share/jupyter/labextensions/jupyterlab-notechat/package.json
jupyterlab_notechat-1.2.4.data/data/share/jupyter/labextensions/jupyterlab-notechat/schemas/jupyterlab-notechat/package.json.orig
jupyterlab_notechat-1.2.4.data/data/share/jupyter/labextensions/jupyterlab-notechat/schemas/jupyterlab-notechat/plugin.json
jupyterlab_notechat-1.2.4.data/data/share/jupyter/labextensions/jupyterlab-notechat/static/352.c79c4ba6bcd91d1804fa.js
jupyterlab_notechat-1.2.4.data/data/share/jupyter/labextensions/jupyterlab-notechat/static/728.d8d3e114803a899f683c.js
jupyterlab_notechat-1.2.4.data/data/share/jupyter/labextensions/jupyterlab-notechat/static/remoteEntry.6725e473b1e9a101c937.js
jupyterlab_notechat-1.2.4.data/data/share/jupyter/labextensions/jupyterlab-notechat/static/style.js
jupyterlab_notechat-1.2.4.data/data/share/jupyter/labextensions/jupyterlab-notechat/static/third-party-licenses.json
jupyterlab_notechat-1.2.4.data/data/share/jupyter/labextensions/jupyterlab-notechat/install.json
jupyterlab_notechat-1.2.4.dist-info/METADATA
jupyterlab_notechat-1.2.4.dist-info/WHEEL
jupyterlab_notechat-1.2.4.dist-info/licenses/LICENSE
jupyterlab_notechat-1.2.4.dist-info/RECORD
