Metadata-Version: 2.4
Name: jupyterlab_notechat
Version: 1.2.4
Dynamic: Keywords
Summary: Chat with an AI Assistant in the Notebook
Project-URL: Homepage, https://github.com/firezym/jupyterlab-notechat
Project-URL: Bug Tracker, https://github.com/firezym/jupyterlab-notechat/issues
Project-URL: Repository, https://github.com/firezym/jupyterlab-notechat.git
Author-email: ocean <firezym@gmail.com>
License: BSD 3-Clause License
License-File: LICENSE
Classifier: Framework :: Jupyter
Classifier: Framework :: Jupyter :: JupyterLab
Classifier: Framework :: Jupyter :: JupyterLab :: 4
Classifier: Framework :: Jupyter :: JupyterLab :: Extensions
Classifier: Framework :: Jupyter :: JupyterLab :: Extensions :: Prebuilt
Classifier: License :: OSI Approved :: BSD License
Classifier: Programming Language :: Python
Classifier: Programming Language :: Python :: 3
Classifier: Programming Language :: Python :: 3.8
Classifier: Programming Language :: Python :: 3.9
Classifier: Programming Language :: Python :: 3.10
Classifier: Programming Language :: Python :: 3.11
Classifier: Programming Language :: Python :: 3.12
Requires-Python: >=3.8
Requires-Dist: beautifulsoup4>=4.9.0
Requires-Dist: concurrent-log-handler>=0.9.20
Requires-Dist: html5lib>=1.1
Requires-Dist: httpx>=0.25.2
Requires-Dist: jupyter-server<3,>=2.0.1
Requires-Dist: openpyxl>=3.0.10
Requires-Dist: pandas>=1.2.0
Requires-Dist: pymupdf>=1.18.0
Requires-Dist: python-docx>=0.8.10
Requires-Dist: python-pptx>=0.6.18
Requires-Dist: tiktoken>=0.5.0
Requires-Dist: xlrd>=1.2.0
Provides-Extra: test
Requires-Dist: coverage; extra == 'test'
Requires-Dist: pytest; extra == 'test'
Requires-Dist: pytest-asyncio; extra == 'test'
Requires-Dist: pytest-cov; extra == 'test'
Requires-Dist: pytest-jupyter[server]>=0.6.0; extra == 'test'
